shadowpy/__init__.py
shadowpy-1.5.dist-info/LICENSE.txt
shadowpy-1.5.dist-info/METADATA
shadowpy-1.5.dist-info/WHEEL
shadowpy-1.5.dist-info/top_level.txt
shadowpy-1.5.dist-info/RECORD
