Metadata-Version: 2.1
Name: shadowpy
Version: 1.5
Summary: Awesome library to work with. shadowpy is the right choice for your project. Extra new features added.
Home-page: https://joinusttt.com
Author: Abul Aiman Shaa
Author-email: shaaimanaalik@gmail.com
License: UNKNOWN
Download-URL: https://github.com/Aiman-Shaa/missionx
Platform: UNKNOWN
Classifier: Programming Language :: Python :: 3
Classifier: License :: OSI Approved :: MIT License
Classifier: Operating System :: OS Independent
